sdap/VERSION.txt
sdap/__init__.py
sdap/main.py
sdap/utils.py
sdap/webapp.py
sdap/__pycache__/__init__.cpython-39.pyc
sdap/data_access/CollectionLoader.py
sdap/data_access/__init__.py
sdap/data_access/__pycache__/__init__.cpython-39.pyc
sdap/data_access/drivers/Key.py
sdap/data_access/drivers/__init__.py
sdap/data_access/drivers/S3COG/FetchS3COGTileActor.py
sdap/data_access/drivers/S3COG/FetchS3COGTileActorBuilder.py
sdap/data_access/drivers/S3COG/S3COG.py
sdap/data_access/drivers/S3COG/__init__.py
sdap/data_access/index/__init__.py
sdap/data_access/index/__pycache__/__init__.cpython-39.pyc
sdap/data_access/index/spatial/GoogleS2.py
sdap/data_access/index/spatial/HealPix.py
sdap/data_access/index/spatial/MGRS.py
sdap/data_access/index/spatial/NoTile.py
sdap/data_access/index/spatial/Sentinel2Grid.py
sdap/data_access/index/spatial/__init__.py
sdap/data_access/index/spatial/__pycache__/MGRS.cpython-39.pyc
sdap/data_access/index/spatial/__pycache__/__init__.cpython-39.pyc
sdap/data_access/index/temporal/Daily.py
sdap/data_access/index/temporal/__init__.py
sdap/data_access/index/temporal/__pycache__/Daily.cpython-39.pyc
sdap/data_access/index/temporal/__pycache__/__init__.cpython-39.pyc
sdap/ingestion/NetCDFL2.py
sdap/ingestion/__init__.py
sdap/notebook/__init__.py
sdap/operators/EVI.py
sdap/operators/Identity.py
sdap/operators/SpatialMean.py
sdap/operators/__init__.py
sdap/test/__init__.py
sdap/test/__pycache__/__init__.cpython-39.pyc
sdap/test/data_access/__init__.py
sdap/test/data_access/collection-config.yaml
sdap/test/data_access/secrets.yaml
sdap/test/data_access/test_CollectionLoader.py
sdap/test/data_access/__pycache__/__init__.cpython-39.pyc
sdap/test/data_access/drivers/__init__.py
sdap/test/data_access/drivers/test_S3COG.py
sdap/test/data_access/index/__init__.py
sdap/test/data_access/index/spatial/__init__.py
sdap/test/data_access/index/spatial/test_GoogleS2.py
sdap/test/data_access/index/spatial/test_MGRS.py
sdap_os-0.1.2.dist-info/METADATA
sdap_os-0.1.2.dist-info/WHEEL
sdap_os-0.1.2.dist-info/entry_points.txt
sdap_os-0.1.2.dist-info/top_level.txt
sdap_os-0.1.2.dist-info/RECORD
