Metadata-Version: 2.1
Name: sdap-os
Version: 0.1.2
Summary: Demo of usage of object storage for SDAP
Home-page: 
Download-URL: 
Author: SDAP
Author-email: thomas.g.loubrieu@jpl.nasa.gov
License: apache-2.0
Keywords: sdap,cog,s3
Platform: UNKNOWN
Classifier: Intended Audience :: Science/Research
Classifier: License :: OSI Approved :: Apache Software License
Classifier: Operating System :: OS Independent
Classifier: Programming Language :: Python :: 3
Classifier: Topic :: Scientific/Engineering
Requires-Python: >=3.9
Requires-Dist: boto3 (==1.20.20)
Requires-Dist: matplotlib (==3.5.0)
Requires-Dist: geopandas (==0.10.2)
Requires-Dist: utm (==0.7.0)
Requires-Dist: rioxarray (==0.9.0)
Requires-Dist: xarray (==0.20.2)
Requires-Dist: PyYAML (==6.0)
Requires-Dist: pyproj (==3.3.0)
Requires-Dist: ray[default] (==1.9.0)
Requires-Dist: numpy (==1.21.4)
Requires-Dist: fsspec (==2021.11.1)
Requires-Dist: requests (==2.26.0)
Requires-Dist: aiohttp (==3.8.1)
Requires-Dist: scipy (==1.7.3)
Requires-Dist: OWSLib (==0.25.0)
Requires-Dist: s2sphere (==0.2.5)
Requires-Dist: flask-restful (==0.3.9)
Requires-Dist: flask-apispec (==0.11.1)
Provides-Extra: client
Requires-Dist: jupyterlab (==3.3) ; extra == 'client'
Requires-Dist: ipympl (==0.9.1) ; extra == 'client'
Provides-Extra: dev
Requires-Dist: cartopy (==0.20.1) ; extra == 'dev'
Requires-Dist: twine (==4.0.0) ; extra == 'dev'
Provides-Extra: ingestion
Requires-Dist: netCDF4 (==1.5.8) ; extra == 'ingestion'
